fit_extract
