Metadata-Version: 1.0
Name: fit-extract
Version: 1.3.2
Summary: Extracts data from EC-Lab .fit files
Home-page: https://github.com/austinluong/fit-extract
Author: Austin Luong
Author-email: austin1995@gmail.com
License: This is free and unencumbered software released into the public domain.
